CHANGES.rst
MANIFEST.in
README.rst
a.sh
apt.sh
b.sh
becomepil.patch
buildout.cfg
cairo.cfg
minitage-26.cfg
minitage-27.cfg
minitage.cfg
refresh.sh
setup.py
testbuild.sh
tests.sh
agg/copying
agg/include/Makefile.am
agg/include/agg_alpha_mask_u8.h
agg/include/agg_arc.h
agg/include/agg_array.h
agg/include/agg_arrowhead.h
agg/include/agg_basics.h
agg/include/agg_bezier_arc.h
agg/include/agg_bitset_iterator.h
agg/include/agg_blur.h
agg/include/agg_bounding_rect.h
agg/include/agg_bspline.h
agg/include/agg_clip_liang_barsky.h
agg/include/agg_color_gray.h
agg/include/agg_color_rgba.h
agg/include/agg_config.h
agg/include/agg_conv_adaptor_vcgen.h
agg/include/agg_conv_adaptor_vpgen.h
agg/include/agg_conv_bspline.h
agg/include/agg_conv_clip_polygon.h
agg/include/agg_conv_clip_polyline.h
agg/include/agg_conv_clipper.h
agg/include/agg_conv_close_polygon.h
agg/include/agg_conv_concat.h
agg/include/agg_conv_contour.h
agg/include/agg_conv_curve.h
agg/include/agg_conv_dash.h
agg/include/agg_conv_gpc.h
agg/include/agg_conv_marker.h
agg/include/agg_conv_marker_adaptor.h
agg/include/agg_conv_segmentator.h
agg/include/agg_conv_shorten_path.h
agg/include/agg_conv_smooth_poly1.h
agg/include/agg_conv_stroke.h
agg/include/agg_conv_transform.h
agg/include/agg_conv_unclose_polygon.h
agg/include/agg_curves.h
agg/include/agg_dda_line.h
agg/include/agg_ellipse.h
agg/include/agg_ellipse_bresenham.h
agg/include/agg_embedded_raster_fonts.h
agg/include/agg_font_cache_manager.h
agg/include/agg_gamma_functions.h
agg/include/agg_gamma_lut.h
agg/include/agg_glyph_raster_bin.h
agg/include/agg_gradient_lut.h
agg/include/agg_gsv_text.h
agg/include/agg_image_accessors.h
agg/include/agg_image_filters.h
agg/include/agg_line_aa_basics.h
agg/include/agg_math.h
agg/include/agg_math_stroke.h
agg/include/agg_path_length.h
agg/include/agg_path_storage.h
agg/include/agg_path_storage_integer.h
agg/include/agg_pattern_filters_rgba.h
agg/include/agg_pixfmt_amask_adaptor.h
agg/include/agg_pixfmt_gray.h
src/mapnik2.egg-info/PKG-INFO
src/mapnik2.egg-info/SOURCES.txt
src/mapnik2.egg-info/dependency_links.txt
src/mapnik2.egg-info/not-zip-safe
src/mapnik2.egg-info/requires.txt
src/mapnik2.egg-info/top_level.txt