Metadata-Version: 1.1
Name: mapnik2
Version: 2.2.0
Summary: Python bindings for mapnik
Home-page: http://pypi.python.org/pypi/mapnik
Author: Mathieu Le Marec - Pasquet & the mapnik community
Author-email: kiorky@cryptelium.net
License: LGPL
Platform: UNKNOWN
Classifier: Programming Language :: Python
Classifier: Topic :: Software Development :: Libraries :: Python Modules
